aliyun_cert/__init__.py
aliyun_cert/cert.py
aliyun_cert/main.py
aliyun_cert-0.1.4.dist-info/licenses/LICENSE
certbot_dns_aliyun/__init__.py
certbot_dns_aliyun/dns_aliyun.py
aliyun_cert-0.1.4.dist-info/METADATA
aliyun_cert-0.1.4.dist-info/WHEEL
aliyun_cert-0.1.4.dist-info/entry_points.txt
aliyun_cert-0.1.4.dist-info/top_level.txt
aliyun_cert-0.1.4.dist-info/RECORD
