Metadata-Version: 2.4
Name: aliyun-cert
Version: 0.1.4
Author-email: OpenSight <public@opensight.cn>
License: AGPLv3
Project-URL: Homepage, https://github.com/OpenSight/aliyun-cert
Project-URL: Issues, https://github.com/OpenSight/aliyun-cert/issues
Classifier: Development Status :: 4 - Beta
Classifier: Intended Audience :: System Administrators
Classifier: Intended Audience :: Developers
Classifier: License :: OSI Approved :: GNU Affero General Public License v3
Classifier: Operating System :: MacOS
Classifier: Operating System :: POSIX :: Linux
Classifier: Programming Language :: Python :: 3
Classifier: Programming Language :: Python :: 3.9
Classifier: Programming Language :: Python :: 3 :: Only
Classifier: Topic :: System :: Systems Administration
Requires-Python: >=3.9
License-File: LICENSE
Requires-Dist: acme==4.2.0
Requires-Dist: certbot==4.2.0
Requires-Dist: alibabacloud_alidns20150109==4.0.0
Requires-Dist: alibabacloud_cdn20180510==8.0.0
Requires-Dist: alibabacloud_live20161101==2.5.1
Requires-Dist: alibabacloud_cas20200407==3.0.4
Requires-Dist: click==8.1.8
Requires-Dist: rich==14.2.0
Requires-Dist: rich-click==1.9.5
Requires-Dist: python-dateutil==2.9.0
Provides-Extra: test
Requires-Dist: pytest; extra == "test"
Dynamic: license-file
